fresco/__init__.py
fresco/cookie.py
fresco/core.py
fresco/decorators.py
fresco/defaults.py
fresco/exceptions.py
fresco/middleware.py
fresco/multidict.py
fresco/options.py
fresco/py.typed
fresco/request.py
fresco/requestcontext.py
fresco/response.py
fresco/routeargs.py
fresco/routing.py
fresco/static.py
fresco/subrequests.py
fresco/types.py
fresco/tests/__init__.py
fresco/tests/fixtures.py
fresco/tests/test_cookie.py
fresco/tests/test_core.py
fresco/tests/test_decorators.py
fresco/tests/test_exceptions.py
fresco/tests/test_middleware.py
fresco/tests/test_multidict.py
fresco/tests/test_options.py
fresco/tests/test_request.py
fresco/tests/test_requestcontext.py
fresco/tests/test_response.py
fresco/tests/test_routeargs.py
fresco/tests/test_routing.py
fresco/tests/test_static.py
fresco/tests/test_subrequests.py
fresco/tests/util/__init__.py
fresco/tests/util/form_data.py
fresco/tests/util/test_common.py
fresco/tests/util/test_http.py
fresco/tests/util/test_security.py
fresco/tests/util/test_urls.py
fresco/tests/util/test_wsgi.py
fresco/util/__init__.py
fresco/util/cache.py
fresco/util/common.py
fresco/util/contentencodings.py
fresco/util/file.py
fresco/util/http.py
fresco/util/io.py
fresco/util/object.py
fresco/util/security.py
fresco/util/textproc.py
fresco/util/urls.py
fresco/util/wsgi.py
fresco-3.8.0.dist-info/licenses/LICENSE.txt
fresco-3.8.0.dist-info/METADATA
fresco-3.8.0.dist-info/WHEEL
fresco-3.8.0.dist-info/top_level.txt
fresco-3.8.0.dist-info/RECORD
