Metadata-Version: 2.4
Name: fresco
Version: 3.8.0
Summary: A Web/WSGI micro-framework
Author-email: Oliver Cope <oliver@redgecko.org>
License-Expression: Apache-2.0
Project-URL: Homepage, https://ollycope.com/software/fresco/latest/
Keywords: wsgi,web,www,framework
Classifier: Development Status :: 5 - Production/Stable
Classifier: Environment :: Web Environment
Classifier: Intended Audience :: Developers
Classifier: Operating System :: OS Independent
Classifier: Programming Language :: Python :: 3
Classifier: Topic :: Internet :: WWW/HTTP :: Dynamic Content
Classifier: Topic :: Internet :: WWW/HTTP :: WSGI
License-File: LICENSE.txt
Dynamic: license-file
